activepaths/__init__.py
activepaths/analysis.py
activepaths/core.py
activepaths/dynamics/__init__.py
activepaths/dynamics/propagator.py
activepaths/dynamics/rtp.py
activepaths/sampling/__init__.py
activepaths/sampling/tps.py
activepaths/sampling/vps.py
activepaths-0.1.0.dist-info/METADATA
activepaths-0.1.0.dist-info/WHEEL
activepaths-0.1.0.dist-info/licenses/LICENSE
activepaths-0.1.0.dist-info/RECORD
