Metadata-Version: 2.4
Name: activepaths
Version: 0.1.0
Summary: A library for rare dynamical event sampling in non-equilibrium systems.
Project-URL: Homepage, https://github.com/kuslavicek/activepaths
Project-URL: Repository, https://github.com/kuslavicek/activepaths.git
Author-email: kuslavicek <kuslavicek@gmail.com>
License: MIT
License-File: LICENSE
Requires-Python: >=3.8
Requires-Dist: numpy
